autox/__init__.py
autox/constants.py
autox/run.py
autox/sql.py
autox/core/__init__.py
autox/core/myconfig.py
autox/core/mydb.py
autox/core/myemail.py
autox/core/mylog.py
autox/core/myrequest.py
autox/core/myresponse.py
autox/model/__init__.py
autox/model/htmlparser.py
autox/model/model.py
autox/model/report.py
autox/model/template
autox/model/__pycache__/__init__.cpython-37.pyc
autox/model/__pycache__/htmlparser.cpython-37.pyc
autox/model/__pycache__/model.cpython-37.pyc
autox/model/__pycache__/report.cpython-37.pyc
autox/util/__init__.py
autox/util/common.py
autox/util/deal.py
autox/util/others.py
autox-0.2.3.dist-info/METADATA
autox-0.2.3.dist-info/WHEEL
autox-0.2.3.dist-info/top_level.txt
autox-0.2.3.dist-info/RECORD
