Metadata-Version: 2.1
Name: autox
Version: 0.2.3
Summary: api test
Home-page: https://github.com/zatena/autox.git
Author: echoz
Author-email: zatena@163.com
License: UNKNOWN
Keywords: automatic api test python
Platform: UNKNOWN
Requires-Dist: certifi (==2019.3.9)
Requires-Dist: chardet (==3.0.4)
Requires-Dist: idna (==2.8)
Requires-Dist: requests (==2.21.0)
Requires-Dist: urllib3 (==1.24.3)
Requires-Dist: jsonpath (==0.81)
Requires-Dist: pymysql (==0.9.2)
